torchisp/__init__.py
torchisp/dataloader.py
torchisp/inverse_pipeline.py
torchisp/pipeline.py
torchisp/rgb2rggb.py
torchisp/rggb2rgb.py
torchisp/module/__init__.py
torchisp/module/ccm.py
torchisp/module/wbc.py
torchisp-0.1.1.dist-info/LICENSE
torchisp-0.1.1.dist-info/METADATA
torchisp-0.1.1.dist-info/WHEEL
torchisp-0.1.1.dist-info/top_level.txt
torchisp-0.1.1.dist-info/RECORD
