Metadata-Version: 2.1
Name: torchisp
Version: 0.1.1
Summary: A PyTorch-based image signal processing tool for converting RGGB to RGB images.
Home-page: https://github.com/GenBill/TorchISP
Author: GenBill
Author-email: genbill97@gmail.com
Classifier: Development Status :: 3 - Alpha
Classifier: Intended Audience :: Developers
Classifier: License :: OSI Approved :: MIT License
Classifier: Programming Language :: Python :: 3
Classifier: Programming Language :: Python :: 3.7
Classifier: Programming Language :: Python :: 3.8
Classifier: Programming Language :: Python :: 3.9
Requires-Python: >=3.7
License-File: LICENSE
